nonebot_plugin_cave/__init__.py
nonebot_plugin_cave/data_source.py
nonebot_plugin_cave-1.1.12.dist-info/LICENSE
nonebot_plugin_cave-1.1.12.dist-info/METADATA
nonebot_plugin_cave-1.1.12.dist-info/WHEEL
nonebot_plugin_cave-1.1.12.dist-info/top_level.txt
nonebot_plugin_cave-1.1.12.dist-info/RECORD
