Metadata-Version: 2.1
Name: nonebot-plugin-cave
Version: 1.1.12
Summary: A cave plugin in Nonebot2
Home-page: https://github.com/hmzz804/nonebot_plugin_cave
Author: hmzz804
Author-email: 2166908863@qq.com
License: MIT License
Classifier: Programming Language :: Python :: 3
Classifier: Operating System :: OS Independent
License-File: LICENSE
Requires-Dist: nonebot2 >=2.0.0-beta.2
Requires-Dist: nonebot-adapter-onebot >=2.0.0b1
Requires-Dist: nonebot-adapter-onebot
Requires-Dist: requests
